{
    "openapi": "3.0.0",
    "info": {
        "title": "API Reservas",
        "version": "1.0.0"
    },
    "paths": {
        "/api/deportes": {
            "get": {
                "tags": [
                    "Deporte"
                ],
                "summary": "Mostrar deportes",
                "responses": {
                    "200": {
                        "description": "Mostrar todos los deportes."
                    },
                    "default": {
                        "description": "Ha ocurrido un error."
                    }
                }
            },
            "post": {
                "tags": [
                    "Deporte"
                ],
                "summary": "Crear deporte",
                "operationId": "84c5f6d7062e13022261e2cf7efdf1bd",
                "requestBody": {
                    "content": {
                        "application/json": {
                            "schema": {
                                "properties": {
                                    "": {
                                        "properties": {
                                            "nombre": {
                                                "type": "string"
                                            }
                                        },
                                        "type": "object"
                                    }
                                },
                                "type": "object",
                                "example": {
                                    "nombre": "example"
                                }
                            }
                        }
                    }
                },
                "responses": {
                    "200": {
                        "description": "success",
                        "content": {
                            "application/json": {
                                "schema": {
                                    "properties": {
                                        "id": {
                                            "type": "number",
                                            "example": 1
                                        },
                                        "name": {
                                            "type": "string",
                                            "example": "title"
                                        },
                                        "updated_at": {
                                            "type": "string",
                                            "example": "2021-12-11T09:25:53.000000Z"
                                        },
                                        "created_at": {
                                            "type": "string",
                                            "example": "2021-12-11T09:25:53.000000Z"
                                        }
                                    },
                                    "type": "object"
                                }
                            }
                        }
                    },
                    "400": {
                        "description": "invalid",
                        "content": {
                            "application/json": {
                                "schema": {
                                    "properties": {
                                        "msg": {
                                            "type": "string",
                                            "example": "fail"
                                        }
                                    },
                                    "type": "object"
                                }
                            }
                        }
                    }
                }
            }
        },
        "/api/deportes/{id}": {
            "put": {
                "tags": [
                    "Deporte"
                ],
                "summary": "Update Deportes",
                "operationId": "ffc1a5b76c3ba57bed14da8115437db2",
                "parameters": [
                    {
                        "name": "id",
                        "in": "path",
                        "required": true,
                        "schema": {
                            "type": "string"
                        }
                    }
                ],
                "requestBody": {
                    "content": {
                        "application/json": {
                            "schema": {
                                "properties": {
                                    "": {
                                        "properties": {
                                            "nombre": {
                                                "type": "string"
                                            }
                                        },
                                        "type": "object"
                                    }
                                },
                                "type": "object",
                                "example": {
                                    "nombre": "nuevo nombre"
                                }
                            }
                        }
                    }
                },
                "responses": {
                    "200": {
                        "description": "success",
                        "content": {
                            "application/json": {
                                "schema": {
                                    "properties": {
                                        "id": {
                                            "type": "number",
                                            "example": 1
                                        },
                                        "title": {
                                            "type": "string",
                                            "example": "title"
                                        },
                                        "content": {
                                            "type": "string",
                                            "example": "content"
                                        },
                                        "updated_at": {
                                            "type": "string",
                                            "example": "2021-12-11T09:25:53.000000Z"
                                        },
                                        "created_at": {
                                            "type": "string",
                                            "example": "2021-12-11T09:25:53.000000Z"
                                        }
                                    },
                                    "type": "object"
                                }
                            }
                        }
                    }
                }
            },
            "delete": {
                "tags": [
                    "Deporte"
                ],
                "summary": "Delete Todo",
                "operationId": "7e35185b88d82f822f8e9693a84eb6b6",
                "parameters": [
                    {
                        "name": "id",
                        "in": "path",
                        "required": true,
                        "schema": {
                            "type": "string"
                        }
                    }
                ],
                "responses": {
                    "200": {
                        "description": "success",
                        "content": {
                            "application/json": {
                                "schema": {
                                    "properties": {
                                        "msg": {
                                            "type": "string",
                                            "example": "deleted succesfully"
                                        }
                                    },
                                    "type": "object"
                                }
                            }
                        }
                    }
                }
            }
        },
        "/api/pistas": {
            "get": {
                "tags": [
                    "Pistas"
                ],
                "summary": "Mostrar pistas existentes",
                "responses": {
                    "200": {
                        "description": "Mostrar todas las pistas."
                    },
                    "default": {
                        "description": "Ha ocurrido un error."
                    }
                }
            },
            "post": {
                "tags": [
                    "Pistas"
                ],
                "summary": "Crear Pista",
                "operationId": "7346b20f147745cba0c2e785840957b0",
                "requestBody": {
                    "content": {
                        "application/json": {
                            "schema": {
                                "properties": {
                                    "": {
                                        "properties": {
                                            "deporte": {
                                                "type": "number"
                                            }
                                        },
                                        "type": "object"
                                    }
                                },
                                "type": "object",
                                "example": {
                                    "deporte": "2"
                                }
                            }
                        }
                    }
                },
                "responses": {
                    "200": {
                        "description": "success",
                        "content": {
                            "application/json": {
                                "schema": {
                                    "properties": {
                                        "id": {
                                            "type": "number",
                                            "example": 1
                                        },
                                        "deporte": {
                                            "type": "number",
                                            "example": "title"
                                        }
                                    },
                                    "type": "object"
                                }
                            }
                        }
                    },
                    "201": {
                        "description": "success",
                        "content": {
                            "application/json": {
                                "schema": {
                                    "properties": {
                                        "id": {
                                            "type": "number",
                                            "example": 1
                                        },
                                        "deporte": {
                                            "type": "number",
                                            "example": "title"
                                        }
                                    },
                                    "type": "object"
                                }
                            }
                        }
                    },
                    "400": {
                        "description": "invalid",
                        "content": {
                            "application/json": {
                                "schema": {
                                    "properties": {
                                        "msg": {
                                            "type": "string",
                                            "example": "fail"
                                        }
                                    },
                                    "type": "object"
                                }
                            }
                        }
                    }
                }
            }
        },
        "/api/busqueda/{fecha}&{socio}&{deporte}": {
            "get": {
                "tags": [
                    "Búsqueda pistas"
                ],
                "summary": "Mostrar las pistas",
                "operationId": "fe671bc696aee3359ec38f07f1bfba73",
                "parameters": [
                    {
                        "name": "fecha",
                        "in": "path",
                        "description": "Fecha de la reserva",
                        "required": true
                    },
                    {
                        "name": "socio",
                        "in": "path",
                        "description": "Email del socio que quiere reservar",
                        "required": true
                    },
                    {
                        "name": "deporte",
                        "in": "path",
                        "description": "Deporte",
                        "required": true
                    }
                ],
                "responses": {
                    "200": {
                        "description": "Mostrar todas las reservas.",
                        "content": {
                            "application/json": {}
                        }
                    },
                    "default": {
                        "description": "Ha ocurrido un error."
                    }
                }
            }
        },
        "/api/pistas/{id}": {
            "put": {
                "tags": [
                    "Pistas"
                ],
                "summary": "Update Pistas",
                "operationId": "c9868866a8ba8c6af9821444d6dc7148",
                "parameters": [
                    {
                        "name": "id",
                        "in": "path",
                        "required": true,
                        "schema": {
                            "type": "string"
                        }
                    }
                ],
                "requestBody": {
                    "content": {
                        "application/json": {
                            "schema": {
                                "properties": {
                                    "": {
                                        "properties": {
                                            "deporte": {
                                                "type": "number"
                                            }
                                        },
                                        "type": "object"
                                    }
                                },
                                "type": "object",
                                "example": {
                                    "deporte": "3"
                                }
                            }
                        }
                    }
                },
                "responses": {
                    "200": {
                        "description": "success",
                        "content": {
                            "application/json": {
                                "schema": {
                                    "properties": {
                                        "id": {
                                            "type": "number",
                                            "example": 1
                                        },
                                        "title": {
                                            "type": "string",
                                            "example": "title"
                                        },
                                        "content": {
                                            "type": "string",
                                            "example": "content"
                                        }
                                    },
                                    "type": "object"
                                }
                            }
                        }
                    },
                    "201": {
                        "description": "success",
                        "content": {
                            "application/json": {
                                "schema": {
                                    "properties": {
                                        "id": {
                                            "type": "number",
                                            "example": 1
                                        },
                                        "deporte": {
                                            "type": "number",
                                            "example": "title"
                                        }
                                    },
                                    "type": "object"
                                }
                            }
                        }
                    }
                }
            },
            "delete": {
                "tags": [
                    "Pistas"
                ],
                "summary": "Delete Pistas",
                "operationId": "a218f6084b76ba082159d303e707854f",
                "parameters": [
                    {
                        "name": "id",
                        "in": "path",
                        "required": true,
                        "schema": {
                            "type": "string"
                        }
                    }
                ],
                "responses": {
                    "200": {
                        "description": "success",
                        "content": {
                            "application/json": {
                                "schema": {
                                    "properties": {
                                        "msg": {
                                            "type": "string",
                                            "example": "deleted succesfully"
                                        }
                                    },
                                    "type": "object"
                                }
                            }
                        }
                    }
                }
            }
        },
        "/api/reservas": {
            "get": {
                "tags": [
                    "Reservas"
                ],
                "summary": "Mostrar las reservas",
                "responses": {
                    "200": {
                        "description": "Mostrar todas las reservas."
                    },
                    "default": {
                        "description": "Ha ocurrido un error."
                    }
                }
            },
            "post": {
                "tags": [
                    "Reservas"
                ],
                "summary": "Crear reserva",
                "operationId": "3b0d25aeb18200cc0887c6cb9d929934",
                "requestBody": {
                    "content": {
                        "application/json": {
                            "schema": {
                                "properties": {
                                    "": {
                                        "properties": {
                                            "socio": {
                                                "type": "number"
                                            },
                                            "pista": {
                                                "type": "number"
                                            },
                                            "fecha": {
                                                "type": "string"
                                            }
                                        },
                                        "type": "object"
                                    }
                                },
                                "type": "object",
                                "example": {
                                    "socio": "1",
                                    "pista": "1",
                                    "fecha": "2022-11-07 10:00:00"
                                }
                            }
                        }
                    }
                },
                "responses": {
                    "200": {
                        "description": "success",
                        "content": {
                            "application/json": {
                                "schema": {
                                    "properties": {
                                        "id": {
                                            "type": "number",
                                            "example": 1
                                        },
                                        "socio": {
                                            "type": "number",
                                            "example": 1
                                        },
                                        "pista": {
                                            "type": "number",
                                            "example": 1
                                        },
                                        "fecha": {
                                            "type": "string",
                                            "example": "2022-11-07 10:00:00"
                                        }
                                    },
                                    "type": "object"
                                }
                            }
                        }
                    },
                    "400": {
                        "description": "invalid",
                        "content": {
                            "application/json": {
                                "schema": {
                                    "properties": {
                                        "msg": {
                                            "type": "string",
                                            "example": "fail"
                                        }
                                    },
                                    "type": "object"
                                }
                            }
                        }
                    }
                }
            }
        },
        "/api/listado/{fecha}": {
            "get": {
                "tags": [
                    "Listado reservas"
                ],
                "summary": "Mostrar las reservas",
                "operationId": "a050534dd8099fdae0c0a181e199343f",
                "parameters": [
                    {
                        "name": "fecha",
                        "in": "path",
                        "description": "Fecha de la reserva",
                        "required": true
                    }
                ],
                "responses": {
                    "200": {
                        "description": "Mostrar todas las reservas.",
                        "content": {
                            "application/json": {}
                        }
                    },
                    "default": {
                        "description": "Ha ocurrido un error."
                    }
                }
            }
        },
        "/api/reservas/{id}": {
            "put": {
                "tags": [
                    "Reservas"
                ],
                "summary": "Update Reservas",
                "operationId": "91fe86a4a06c23ace3ffc53de226b866",
                "parameters": [
                    {
                        "name": "id",
                        "in": "path",
                        "required": true,
                        "schema": {
                            "type": "string"
                        }
                    }
                ],
                "requestBody": {
                    "content": {
                        "application/json": {
                            "schema": {
                                "properties": {
                                    "": {
                                        "properties": {
                                            "socio": {
                                                "type": "number"
                                            },
                                            "pista": {
                                                "type": "number"
                                            },
                                            "fecha": {
                                                "type": "string"
                                            }
                                        },
                                        "type": "object"
                                    }
                                },
                                "type": "object",
                                "example": {
                                    "socio": "1",
                                    "pista": "1",
                                    "fecha": "2022-11-07 10:00:00"
                                }
                            }
                        }
                    }
                },
                "responses": {
                    "200": {
                        "description": "success",
                        "content": {
                            "application/json": {
                                "schema": {
                                    "properties": {
                                        "id": {
                                            "type": "number",
                                            "example": 1
                                        },
                                        "socio": {
                                            "type": "number",
                                            "example": 1
                                        },
                                        "pista": {
                                            "type": "number",
                                            "example": 1
                                        },
                                        "fecha": {
                                            "type": "string",
                                            "example": "2022-11-07 10:00:00"
                                        }
                                    },
                                    "type": "object"
                                }
                            }
                        }
                    }
                }
            },
            "delete": {
                "tags": [
                    "Reservas"
                ],
                "summary": "Delete Reserva",
                "operationId": "992ae788935b42ab455ff366e9887ab7",
                "parameters": [
                    {
                        "name": "id",
                        "in": "path",
                        "required": true,
                        "schema": {
                            "type": "string"
                        }
                    }
                ],
                "responses": {
                    "200": {
                        "description": "success",
                        "content": {
                            "application/json": {
                                "schema": {
                                    "properties": {
                                        "msg": {
                                            "type": "string",
                                            "example": "deleted succesfully"
                                        }
                                    },
                                    "type": "object"
                                }
                            }
                        }
                    }
                }
            }
        },
        "/api/socios": {
            "get": {
                "tags": [
                    "Socios"
                ],
                "summary": "Mostrar los socios",
                "responses": {
                    "200": {
                        "description": "Mostrar todos los socios."
                    },
                    "default": {
                        "description": "Ha ocurrido un error."
                    }
                }
            },
            "post": {
                "tags": [
                    "Socios"
                ],
                "summary": "Crear socio",
                "operationId": "ff6e4227b8e8553f9b37593b313f1ad3",
                "requestBody": {
                    "content": {
                        "application/json": {
                            "schema": {
                                "properties": {
                                    "": {
                                        "properties": {
                                            "name": {
                                                "type": "string"
                                            },
                                            "email": {
                                                "type": "string"
                                            }
                                        },
                                        "type": "object"
                                    }
                                },
                                "type": "object",
                                "example": {
                                    "name": "example",
                                    "email": "example@gmail.com"
                                }
                            }
                        }
                    }
                },
                "responses": {
                    "200": {
                        "description": "success",
                        "content": {
                            "application/json": {
                                "schema": {
                                    "properties": {
                                        "id": {
                                            "type": "number",
                                            "example": 1
                                        },
                                        "name": {
                                            "type": "string",
                                            "example": "nombre"
                                        },
                                        "email": {
                                            "type": "string",
                                            "example": "nombre@gmail.com"
                                        }
                                    },
                                    "type": "object"
                                }
                            }
                        }
                    },
                    "400": {
                        "description": "invalid",
                        "content": {
                            "application/json": {
                                "schema": {
                                    "properties": {
                                        "msg": {
                                            "type": "string",
                                            "example": "fail"
                                        }
                                    },
                                    "type": "object"
                                }
                            }
                        }
                    }
                }
            }
        },
        "/api/socios/{id}": {
            "put": {
                "tags": [
                    "Socios"
                ],
                "summary": "Update Socios",
                "operationId": "bbaba4d26088d030dcffacfaf8c01144",
                "parameters": [
                    {
                        "name": "id",
                        "in": "path",
                        "required": true,
                        "schema": {
                            "type": "string"
                        }
                    }
                ],
                "requestBody": {
                    "content": {
                        "application/json": {
                            "schema": {
                                "properties": {
                                    "": {
                                        "properties": {
                                            "name": {
                                                "type": "string"
                                            },
                                            "email": {
                                                "type": "string"
                                            }
                                        },
                                        "type": "object"
                                    }
                                },
                                "type": "object",
                                "example": {
                                    "name": "nuevonombre",
                                    "email": "nuevocorreo@gmail.com"
                                }
                            }
                        }
                    }
                },
                "responses": {
                    "200": {
                        "description": "success",
                        "content": {
                            "application/json": {
                                "schema": {
                                    "properties": {
                                        "id": {
                                            "type": "number",
                                            "example": 1
                                        },
                                        "name": {
                                            "type": "string",
                                            "example": "title"
                                        },
                                        "email": {
                                            "type": "string",
                                            "example": "content"
                                        }
                                    },
                                    "type": "object"
                                }
                            }
                        }
                    }
                }
            },
            "delete": {
                "tags": [
                    "Socios"
                ],
                "summary": "Delete Socios",
                "operationId": "99602f4b52b6cdaed1c76ef88e28b71e",
                "parameters": [
                    {
                        "name": "id",
                        "in": "path",
                        "required": true,
                        "schema": {
                            "type": "string"
                        }
                    }
                ],
                "responses": {
                    "200": {
                        "description": "success",
                        "content": {
                            "application/json": {
                                "schema": {
                                    "properties": {
                                        "msg": {
                                            "type": "string",
                                            "example": "deleted succesfully"
                                        }
                                    },
                                    "type": "object"
                                }
                            }
                        }
                    }
                }
            }
        },
        "/api/usuarios": {
            "get": {
                "tags": [
                    "Usuarios"
                ],
                "summary": "Mostrar usuarios",
                "operationId": "def965050e08426437080b9f93650872",
                "responses": {
                    "200": {
                        "description": "Mostrar todos los deportes."
                    },
                    "default": {
                        "description": "Ha ocurrido un error."
                    }
                }
            },
            "post": {
                "tags": [
                    "Usuarios"
                ],
                "summary": "Crear usuario",
                "operationId": "88700e31d86fba96458ff6d229350cfc",
                "requestBody": {
                    "content": {
                        "application/json": {
                            "schema": {
                                "properties": {
                                    "": {
                                        "properties": {
                                            "name": {
                                                "type": "string"
                                            },
                                            "email": {
                                                "type": "string"
                                            },
                                            "password": {
                                                "type": "string"
                                            }
                                        },
                                        "type": "object"
                                    }
                                },
                                "type": "object",
                                "example": {
                                    "name": "",
                                    "email": "",
                                    "password": ""
                                }
                            }
                        }
                    }
                },
                "responses": {
                    "200": {
                        "description": "success",
                        "content": {
                            "application/json": {
                                "schema": {
                                    "properties": {
                                        "name": {
                                            "type": "string",
                                            "example": ""
                                        },
                                        "email": {
                                            "type": "string",
                                            "example": ""
                                        },
                                        "password": {
                                            "type": "string",
                                            "example": ""
                                        }
                                    },
                                    "type": "object"
                                }
                            }
                        }
                    },
                    "400": {
                        "description": "invalid",
                        "content": {
                            "application/json": {
                                "schema": {
                                    "properties": {
                                        "msg": {
                                            "type": "string",
                                            "example": "fail"
                                        }
                                    },
                                    "type": "object"
                                }
                            }
                        }
                    }
                }
            }
        },
        "/api/usuarios/{id}": {
            "put": {
                "tags": [
                    "Usuarios"
                ],
                "summary": "Update Users",
                "operationId": "7bc446ec56fee5b08c575b930697a5f9",
                "parameters": [
                    {
                        "name": "id",
                        "in": "path",
                        "required": true,
                        "schema": {
                            "type": "string"
                        }
                    }
                ],
                "requestBody": {
                    "content": {
                        "application/json": {
                            "schema": {
                                "properties": {
                                    "": {
                                        "properties": {
                                            "name": {
                                                "type": "string"
                                            },
                                            "email": {
                                                "type": "string"
                                            },
                                            "password": {
                                                "type": "password"
                                            }
                                        },
                                        "type": "object"
                                    }
                                },
                                "type": "object",
                                "example": {
                                    "name": "",
                                    "email": "",
                                    "password": ""
                                }
                            }
                        }
                    }
                },
                "responses": {
                    "200": {
                        "description": "success",
                        "content": {
                            "application/json": {
                                "schema": {
                                    "properties": {
                                        "name": {
                                            "type": "string",
                                            "example": ""
                                        },
                                        "email": {
                                            "type": "string",
                                            "example": ""
                                        },
                                        "password": {
                                            "type": "password",
                                            "example": ""
                                        }
                                    },
                                    "type": "object"
                                }
                            }
                        }
                    },
                    "400": {
                        "description": "invalid",
                        "content": {
                            "application/json": {
                                "schema": {
                                    "properties": {
                                        "msg": {
                                            "type": "string",
                                            "example": "fail"
                                        }
                                    },
                                    "type": "object"
                                }
                            }
                        }
                    }
                }
            },
            "delete": {
                "tags": [
                    "Usuarios"
                ],
                "summary": "Delete User",
                "operationId": "7fa713aab598a149659eb2db9703636d",
                "parameters": [
                    {
                        "name": "id",
                        "in": "path",
                        "required": true,
                        "schema": {
                            "type": "string"
                        }
                    }
                ],
                "responses": {
                    "200": {
                        "description": "success",
                        "content": {
                            "application/json": {
                                "schema": {
                                    "properties": {
                                        "msg": {
                                            "type": "string",
                                            "example": "deleted succesfully"
                                        }
                                    },
                                    "type": "object"
                                }
                            }
                        }
                    }
                }
            }
        }
    },
    "components": {
        "securitySchemes": {
            "bearerAuth": {
                "type": "http",
                "name": "bearerAuth",
                "in": "header",
                "bearerFormat": "JWT",
                "scheme": "bearer"
            }
        }
    }
}